{
  "schema": "worldbuilder.table.v1",
  "id": "travel_sea_d100",
  "title": "Sea Travel Encounters",
  "selectors": {
    "type": "table",
    "travel": "sea",
    "encounter_type": "exploration",
    "source": "homebrew"
  },
  "die": "d100",
  "entries": [
    {
      "range": [
        1,
        5
      ],
      "text": "Sudden squall batters the ship",
      "encounter_type": "exploration",
      "cr_bucket": "cr:0-1",
      "monster_suggestions": [],
      "needs_homebrew": false,
      "notes": "Hazard"
    },
    {
      "range": [
        6,
        10
      ],
      "text": "Dolphins escort the vessel",
      "encounter_type": "exploration",
      "cr_bucket": "cr:0-1",
      "monster_suggestions": [],
      "needs_homebrew": false,
      "notes": ""
    },
    {
      "range": [
        11,
        15
      ],
      "text": "Pirate skiff approaches",
      "encounter_type": "exploration",
      "cr_bucket": "cr:2-4",
      "monster_suggestions": [
        {
          "name": "Bandit",
          "count": "2d6",
          "source": "srd",
          "notes": ""
        },
        {
          "name": "Bandit Captain",
          "count": "1",
          "source": "srd",
          "notes": ""
        }
      ],
      "needs_homebrew": false,
      "notes": "Pirates as bandits"
    },
    {
      "range": [
        16,
        20
      ],
      "text": "Fog bank\u2014navigation test",
      "encounter_type": "exploration",
      "cr_bucket": "cr:0-1",
      "monster_suggestions": [],
      "needs_homebrew": false,
      "notes": ""
    },
    {
      "range": [
        21,
        25
      ],
      "text": "Reef sharks circle debris",
      "encounter_type": "exploration",
      "cr_bucket": "cr:2-4",
      "monster_suggestions": [
        {
          "name": "Reef Shark",
          "count": "1d4",
          "source": "homebrew",
          "notes": "Use SRD Giant Shark if available, otherwise homebrew"
        }
      ],
      "needs_homebrew": true,
      "notes": "No guaranteed SRD reef shark"
    },
    {
      "range": [
        26,
        30
      ],
      "text": "Shipwreck survivors request aid",
      "encounter_type": "exploration",
      "cr_bucket": "cr:0-1",
      "monster_suggestions": [],
      "needs_homebrew": false,
      "notes": ""
    },
    {
      "range": [
        31,
        35
      ],
      "text": "Sea hag\u2019s omen on the waves",
      "encounter_type": "exploration",
      "cr_bucket": "cr:2-4",
      "monster_suggestions": [
        {
          "name": "Sea Hag",
          "count": "1",
          "source": "srd",
          "notes": ""
        }
      ],
      "needs_homebrew": false,
      "notes": ""
    },
    {
      "range": [
        36,
        40
      ],
      "text": "Floating wreck hides scavengers",
      "encounter_type": "exploration",
      "cr_bucket": "cr:2-4",
      "monster_suggestions": [
        {
          "name": "Bandit",
          "count": "1d6",
          "source": "srd",
          "notes": ""
        }
      ],
      "needs_homebrew": false,
      "notes": ""
    },
    {
      "range": [
        41,
        45
      ],
      "text": "Storm damages rigging",
      "encounter_type": "exploration",
      "cr_bucket": "cr:0-1",
      "monster_suggestions": [],
      "needs_homebrew": false,
      "notes": ""
    },
    {
      "range": [
        46,
        50
      ],
      "text": "Mysterious lights under the water",
      "encounter_type": "exploration",
      "cr_bucket": "cr:0-1",
      "monster_suggestions": [],
      "needs_homebrew": false,
      "notes": "Hook"
    },
    {
      "range": [
        51,
        55
      ],
      "text": "Sahuagin raid (if used)",
      "encounter_type": "exploration",
      "cr_bucket": "cr:5-10",
      "monster_suggestions": [
        {
          "name": "Sahuagin",
          "count": "2d6",
          "source": "homebrew",
          "notes": "Homebrew or SRD if present"
        }
      ],
      "needs_homebrew": true,
      "notes": "Sahuagin SRD status varies by ruleset"
    },
    {
      "range": [
        56,
        60
      ],
      "text": "Merchant convoy\u2014trade opportunity",
      "encounter_type": "exploration",
      "cr_bucket": "cr:0-1",
      "monster_suggestions": [],
      "needs_homebrew": false,
      "notes": ""
    },
    {
      "range": [
        61,
        65
      ],
      "text": "Sea cave discovered at low tide",
      "encounter_type": "exploration",
      "cr_bucket": "cr:0-1",
      "monster_suggestions": [],
      "needs_homebrew": false,
      "notes": ""
    },
    {
      "range": [
        66,
        70
      ],
      "text": "Ghost ship sighted",
      "encounter_type": "exploration",
      "cr_bucket": "cr:0-1",
      "monster_suggestions": [],
      "needs_homebrew": false,
      "notes": ""
    },
    {
      "range": [
        71,
        75
      ],
      "text": "Whirlpool forms ahead",
      "encounter_type": "exploration",
      "cr_bucket": "cr:0-1",
      "monster_suggestions": [],
      "needs_homebrew": false,
      "notes": "Hazard"
    },
    {
      "range": [
        76,
        80
      ],
      "text": "Pirate boarding attempt",
      "encounter_type": "exploration",
      "cr_bucket": "cr:2-4",
      "monster_suggestions": [
        {
          "name": "Bandit",
          "count": "2d6",
          "source": "srd",
          "notes": ""
        },
        {
          "name": "Thug",
          "count": "1d4",
          "source": "srd",
          "notes": ""
        }
      ],
      "needs_homebrew": false,
      "notes": ""
    },
    {
      "range": [
        81,
        85
      ],
      "text": "Underwater ruins visible",
      "encounter_type": "exploration",
      "cr_bucket": "cr:0-1",
      "monster_suggestions": [],
      "needs_homebrew": false,
      "notes": ""
    },
    {
      "range": [
        86,
        90
      ],
      "text": "Massive shadow passes beneath",
      "encounter_type": "exploration",
      "cr_bucket": "cr:0-1",
      "monster_suggestions": [],
      "needs_homebrew": false,
      "notes": "Tease big threat"
    },
    {
      "range": [
        91,
        95
      ],
      "text": "Coastal fort signals for help",
      "encounter_type": "exploration",
      "cr_bucket": "cr:0-1",
      "monster_suggestions": [],
      "needs_homebrew": false,
      "notes": ""
    },
    {
      "range": [
        96,
        99
      ],
      "text": "Treasure flotsam in the water",
      "encounter_type": "exploration",
      "cr_bucket": "cr:0-1",
      "monster_suggestions": [],
      "needs_homebrew": false,
      "notes": ""
    },
    {
      "range": [
        100,
        100
      ],
      "text": "A sea-changed relic surfaces",
      "encounter_type": "exploration",
      "cr_bucket": "cr:0-1",
      "monster_suggestions": [],
      "needs_homebrew": false,
      "notes": "Story beat"
    }
  ]
}